cli_tools_info/__init__.py
cli_tools_info/runner.py
cli_tools_info/utils.py
cli_tools_info/versions.py
cli_tools_info-1.0.5.dist-info/WHEEL
cli_tools_info-1.0.5.dist-info/METADATA
cli_tools_info-1.0.5.dist-info/RECORD
