Metadata-Version: 2.1
Name: cli-tools-info
Version: 1.0.5
Summary: 
Author: Erik Lilja
Author-email: erik@rkllj.io
Requires-Python: >=3.8,<4.0
Classifier: Programming Language :: Python :: 3
Classifier: Programming Language :: Python :: 3.10
Classifier: Programming Language :: Python :: 3.8
Classifier: Programming Language :: Python :: 3.9
Requires-Dist: tabulate (>=0.9.0,<0.10.0)
